yacs_stubgen/__init__.py
yacs_stubgen-0.3.1.dist-info/WHEEL
yacs_stubgen-0.3.1.dist-info/entry_points.txt
yacs_stubgen-0.3.1.dist-info/METADATA
yacs_stubgen-0.3.1.dist-info/RECORD
