Metadata-Version: 2.3
Name: yacs-stubgen
Version: 0.3.1
Summary: Generate stub file for yacs config.
Author: JamzumSum
Author-email: JamzumSum <22952836+JamzumSum@users.noreply.github.com>
License: MIT
Requires-Dist: yacs~=0.1.4
Requires-Python: >=3.10
Project-URL: Bug Tracker, https://github.com/JamzumSum/yacs-stubgen/issues
Project-URL: Homepage, https://github.com/JamzumSum/yacs-stubgen
Project-URL: Repository, https://github.com/JamzumSum/yacs-stubgen
